CHANGES.txt
DEPENDENCES.txt
README.txt
setup.py
src/ng/__init__.py
src/ng.app.rubricator.algorithm.base.egg-info/PKG-INFO
src/ng.app.rubricator.algorithm.base.egg-info/SOURCES.txt
src/ng.app.rubricator.algorithm.base.egg-info/dependency_links.txt
src/ng.app.rubricator.algorithm.base.egg-info/namespace_packages.txt
src/ng.app.rubricator.algorithm.base.egg-info/not-zip-safe
src/ng.app.rubricator.algorithm.base.egg-info/requires.txt
src/ng.app.rubricator.algorithm.base.egg-info/top_level.txt
src/ng/app/__init__.py
src/ng/app/rubricator/__init__.py
src/ng/app/rubricator/algorithm/__init__.py
src/ng/app/rubricator/algorithm/base/__init__.py
src/ng/app/rubricator/algorithm/base/configure.zcml
src/ng/app/rubricator/algorithm/base/exceptions.py
src/ng/app/rubricator/algorithm/base/interfaces.py
src/ng/app/rubricator/algorithm/base/ng.app.rubricator.algorithm.base.txt
src/ng/app/rubricator/algorithm/base/rubricalgorithmbase.py
src/ng/app/rubricator/algorithm/base/browser/__init__.py
src/ng/app/rubricator/algorithm/base/browser/configure.zcml
src/ng/app/rubricator/algorithm/base/browser/reindex.pt
src/ng/app/rubricator/algorithm/base/browser/reindex.py
src/ng/app/rubricator/algorithm/base/etc/ng.app.rubricator.algorithm.base-configure.zcml
src/ng/app/rubricator/algorithm/base/handler/__init__.py
src/ng/app/rubricator/algorithm/base/handler/configure.zcml
src/ng/app/rubricator/algorithm/base/handler/rubrichandler.py
